versionator/__init__.py
versionator/core.py
versionator/middleware.py
versionator/utils.py
versionator/changelog/__init__.py
versionator/changelog/arbitrary_version_pair_fetcher.py
versionator/changelog/changelog.py
versionator/changelog/consecutive_versions_retriever.py
versionator/changelog/diff.py
versionator/changelog/diff_utils.py
versionator/changelog/util.py
versionator/changelog/views/__init__.py
versionator/changelog/views/abstract_changelog_view.py
django_versionator-2.1.dist-info/METADATA
django_versionator-2.1.dist-info/WHEEL
django_versionator-2.1.dist-info/top_level.txt
django_versionator-2.1.dist-info/RECORD
