Metadata-Version: 2.4
Name: django-versionator
Version: 2.1
Home-page: https://github.com/AlexCleduc/django-versionator
Author: AlexCLeduc
Classifier: Programming Language :: Python :: 3
Classifier: License :: OSI Approved :: MIT License
Classifier: Operating System :: OS Independent
Provides-Extra: changelog
Requires-Dist: django-data-fetcher<3,>=2.2; extra == "changelog"
Dynamic: author
Dynamic: classifier
Dynamic: description
Dynamic: description-content-type
Dynamic: home-page
Dynamic: provides-extra
